{
    "paths": [
        {
            "name": "/{api-path}",
            "lambdaFunction": "techtalks",
            "privacy": {
                "open": true
            }
        }
    ],
    "resourceName": "techtalks",
    "apiName": "techtalks",
    "functionArns": [
        {
            "lambdaFunction": "techtalks"
        }
    ],
    "privacy": {
        "auth": 0,
        "unauth": 0,
        "authRoleName": "amplify-techtalks-prod-162210-authRole",
        "unAuthRoleName": "amplify-techtalks-prod-162210-unauthRole"
    },
    "dependsOn": [
        {
            "category": "function",
            "resourceName": "techtalks",
            "attributes": [
                "Name",
                "Arn"
            ]
        }
    ],
    "uuid": "4aaf3a43"
}